{"name": "daiquiri", "metadata": {"name": "daiquiri", "version": "3.3.0", "classifiers": ["Intended Audience :: Information Technology", "Intended Audience :: System Administrators", "License :: OSI Approved :: Apache Software License", "Operating System :: POSIX :: Linux", "Programming Language :: Python", "Programming Language :: Python :: 3", "Programming Language :: Python :: 3.10", "Programming Language :: Python :: 3.11", "Programming Language :: Python :: 3.12", "Programming Language :: Python :: 3.13"], "home_page": null, "license": "Apache 2.0", "documentation_url": null, "dependencies": ["python-json-logger"], "summary": "Library to configure Python logging easily", "upload_time": 1734099836}, "documentation": ["# daiquiri -- Python logging setup helper\n\n```{image} https://img.shields.io/pypi/v/daiquiri.svg\n:alt: Latest Version\n:target: https://pypi.python.org/pypi/daiquiri\n```\n\nThe daiquiri library provides an easy way to configure logging. It also\nprovides some custom formatters and handlers.\n\nYou can read the whole documentation at <http://daiquiri.readthedocs.io/>\n\n- Free software: Apache license\n- Source: <https://github.com/Mergifyio/daiquiri>\n"], "modules": [{"name": "daiquiri.formatter", "documentation": ["Formatters.", "Licensed under the Apache License, Version 2.0 (the \"License\"); you may", "not use this file except in compliance with the License. You may obtain", "a copy of the License at", "http://www.apache.org/licenses/LICENSE-2.0", "Unless required by applicable law or agreed to in writing, software", "distributed under the License is distributed on an \"AS IS\" BASIS, WITHOUT", "WARRANTIES OR CONDITIONS OF ANY KIND, either express or implied. See the", "License for the specific language governing permissions and limitations", "under the License."], "functions": [], "variables": [{"name": "daiquiri.formatter.DEFAULT_FORMAT", "type": null, "documentation": []}, {"name": "daiquiri.formatter.DEFAULT_EXTRAS_FORMAT", "type": null, "documentation": []}, {"name": "daiquiri.formatter.TEXT_FORMATTER", "type": null, "documentation": []}, {"name": "daiquiri.formatter.JSON_FORMATTER", "type": null, "documentation": []}, {"name": "daiquiri.formatter.DATADOG_FORMATTER", "type": null, "documentation": []}], "classes": [{"name": "daiquiri.formatter.ColorFormatter", "bases": ["logging.Formatter"], "methods": [{"name": "daiquiri.formatter.ColorFormatter.add_color", "asynchronous": false, "params": [{"name": "self", "type": null, "default": null}, {"name": "record", "type": {"name": "types.ColoredLogRecord", "xref": {"fqname": "daiquiri.types.ColoredLogRecord", "project": null}, "params": null}, "default": null}], "returns": {"name": "None", "xref": {"fqname": "constants.None", "project": "--std--"}, "params": null}, "documentation": ["Add color to a record."]}, {"name": "daiquiri.formatter.ColorFormatter.remove_color", "asynchronous": false, "params": [{"name": "self", "type": null, "default": null}, {"name": "record", "type": {"name": "types.ColoredLogRecord", "xref": {"fqname": "daiquiri.types.ColoredLogRecord", "project": null}, "params": null}, "default": null}], "returns": {"name": "None", "xref": {"fqname": "constants.None", "project": "--std--"}, "params": null}, "documentation": ["Remove color from a record."]}, {"name": "daiquiri.formatter.ColorFormatter.format", "asynchronous": false, "params": [{"name": "self", "type": null, "default": null}, {"name": "record", "type": {"name": "logging.LogRecord", "xref": {"fqname": "logging.LogRecord", "project": "--std--"}, "params": null}, "default": null}], "returns": {"name": "str", "xref": {"fqname": "functions.str", "project": "--std--"}, "params": null}, "documentation": ["Format a record."]}], "class_variables": [{"name": "daiquiri.formatter.ColorFormatter.LEVEL_COLORS", "type": null, "documentation": []}, {"name": "daiquiri.formatter.ColorFormatter.COLOR_STOP", "type": null, "documentation": []}], "instance_variables": [], "inner_classes": [], "documentation": ["Colorizes log output."]}, {"name": "daiquiri.formatter.ExtrasFormatter", "bases": ["logging.Formatter"], "methods": [{"name": "daiquiri.formatter.ExtrasFormatter.__init__", "asynchronous": false, "params": [{"name": "self", "type": null, "default": null}, {"name": "keywords", "type": {"name": "typing.Optional", "xref": {"fqname": "typing.Optional", "project": "--std--"}, "params": [{"name": "typing.Set", "xref": {"fqname": "typing.Set", "project": "--std--"}, "params": [{"name": "str", "xref": {"fqname": "functions.str", "project": "--std--"}, "params": null}]}]}, "default": "..."}, {"name": "extras_template", "type": {"name": "str", "xref": {"fqname": "functions.str", "project": "--std--"}, "params": null}, "default": "..."}, {"name": "extras_separator", "type": {"name": "str", "xref": {"fqname": "functions.str", "project": "--std--"}, "params": null}, "default": "..."}, {"name": "extras_prefix", "type": {"name": "str", "xref": {"fqname": "functions.str", "project": "--std--"}, "params": null}, "default": "..."}, {"name": "extras_suffix", "type": {"name": "str", "xref": {"fqname": "functions.str", "project": "--std--"}, "params": null}, "default": "..."}, {"name": "*args", "type": {"name": "typing.Any", "xref": {"fqname": "typing.Any", "project": "--std--"}, "params": null}, "default": null}, {"name": "**kwargs", "type": {"name": "typing.Any", "xref": {"fqname": "typing.Any", "project": "--std--"}, "params": null}, "default": null}], "returns": {"name": "None", "xref": {"fqname": "constants.None", "project": "--std--"}, "params": null}, "documentation": []}, {"name": "daiquiri.formatter.ExtrasFormatter.add_extras", "asynchronous": false, "params": [{"name": "self", "type": null, "default": null}, {"name": "record", "type": {"name": "types.ExtrasLogRecord", "xref": {"fqname": "daiquiri.types.ExtrasLogRecord", "project": null}, "params": null}, "default": null}], "returns": {"name": "None", "xref": {"fqname": "constants.None", "project": "--std--"}, "params": null}, "documentation": []}, {"name": "daiquiri.formatter.ExtrasFormatter.remove_extras", "asynchronous": false, "params": [{"name": "self", "type": null, "default": null}, {"name": "record", "type": {"name": "types.ExtrasLogRecord", "xref": {"fqname": "daiquiri.types.ExtrasLogRecord", "project": null}, "params": null}, "default": null}], "returns": {"name": "None", "xref": {"fqname": "constants.None", "project": "--std--"}, "params": null}, "documentation": []}, {"name": "daiquiri.formatter.ExtrasFormatter.format", "asynchronous": false, "params": [{"name": "self", "type": null, "default": null}, {"name": "record", "type": {"name": "logging.LogRecord", "xref": {"fqname": "logging.LogRecord", "project": "--std--"}, "params": null}, "default": null}], "returns": {"name": "str", "xref": {"fqname": "functions.str", "project": "--std--"}, "params": null}, "documentation": []}], "class_variables": [], "instance_variables": [], "inner_classes": [], "documentation": ["Formats extra keywords into %(extras)s placeholder.\n\nAny keywords passed to a logging call will be formatted into a\n\"extras\" string and included in a logging message.\n\nExample:\n    logger.info('my message', extra='keyword')\n\nwill cause an \"extras\" string of:\n    [extra: keyword]\n\nto be inserted into the format in place of %(extras)s.\n\nThe optional `keywords` argument must be passed into the init\nfunction to enable this functionality. Without it normal daiquiri\nformatting will be applied. Any keywords included in the\n`keywords` parameter will not be included in the \"extras\" string.\n\nSpecial keywords:\n\nkeywords\n    A set of strings containing keywords to filter out of the\n    \"extras\" string.\n\nextras_template\n    A format string to use instead of '[{0}: {1}]'\n\nextras_separator\n    What string to \"join\" multiple \"extras\" with.\n\nextras_prefix and extras_suffix\n    Strings which will be prepended and appended to the \"extras\"\n    string respectively. These will only be prepended if the\n    \"extras\" string is not empty."]}, {"name": "daiquiri.formatter.ColorExtrasFormatter", "bases": ["ColorFormatter", "ExtrasFormatter"], "methods": [{"name": "daiquiri.formatter.ColorExtrasFormatter.format", "asynchronous": false, "params": [{"name": "self", "type": null, "default": null}, {"name": "record", "type": {"name": "logging.LogRecord", "xref": {"fqname": "logging.LogRecord", "project": "--std--"}, "params": null}, "default": null}], "returns": {"name": "str", "xref": {"fqname": "functions.str", "project": "--std--"}, "params": null}, "documentation": []}], "class_variables": [], "instance_variables": [], "inner_classes": [], "documentation": ["Combines functionality of ColorFormatter and ExtrasFormatter."]}, {"name": "daiquiri.formatter.DatadogFormatter", "bases": ["jsonlogger.JsonFormatter"], "methods": [{"name": "daiquiri.formatter.DatadogFormatter.__init__", "asynchronous": false, "params": [{"name": "self", "type": null, "default": null}], "returns": {"name": "None", "xref": {"fqname": "constants.None", "project": "--std--"}, "params": null}, "documentation": []}, {"name": "daiquiri.formatter.DatadogFormatter.add_fields", "asynchronous": false, "params": [{"name": "self", "type": null, "default": null}, {"name": "log_record", "type": {"name": "typing.Dict", "xref": {"fqname": "typing.Dict", "project": "--std--"}, "params": [{"name": "str", "xref": {"fqname": "functions.str", "project": "--std--"}, "params": null}, {"name": "typing.Any", "xref": {"fqname": "typing.Any", "project": "--std--"}, "params": null}]}, "default": null}, {"name": "record", "type": {"name": "logging.LogRecord", "xref": {"fqname": "logging.LogRecord", "project": "--std--"}, "params": null}, "default": null}, {"name": "message_dict", "type": {"name": "typing.Dict", "xref": {"fqname": "typing.Dict", "project": "--std--"}, "params": [{"name": "str", "xref": {"fqname": "functions.str", "project": "--std--"}, "params": null}, {"name": "str", "xref": {"fqname": "functions.str", "project": "--std--"}, "params": null}]}, "default": null}], "returns": {"name": "None", "xref": {"fqname": "constants.None", "project": "--std--"}, "params": null}, "documentation": []}], "class_variables": [], "instance_variables": [], "inner_classes": [], "documentation": []}], "exports": []}, {"name": "daiquiri.tests", "documentation": [], "functions": [], "variables": [], "classes": [], "exports": []}, {"name": "daiquiri.tests.test_formatter", "documentation": ["Licensed under the Apache License, Version 2.0 (the \"License\"); you may", "not use this file except in compliance with the License. You may obtain", "a copy of the License at", "http://www.apache.org/licenses/LICENSE-2.0", "Unless required by applicable law or agreed to in writing, software", "distributed under the License is distributed on an \"AS IS\" BASIS, WITHOUT", "WARRANTIES OR CONDITIONS OF ANY KIND, either express or implied. See the", "License for the specific language governing permissions and limitations", "under the License."], "functions": [], "variables": [], "classes": [{"name": "daiquiri.tests.test_formatter.TestColorExtrasFormatter", "bases": ["unittest.TestCase"], "methods": [{"name": "daiquiri.tests.test_formatter.TestColorExtrasFormatter.setUpClass", "asynchronous": false, "params": [{"name": "cls", "type": null, "default": null}], "returns": {"name": "None", "xref": {"fqname": "constants.None", "project": "--std--"}, "params": null}, "documentation": []}, {"name": "daiquiri.tests.test_formatter.TestColorExtrasFormatter.setUp", "asynchronous": false, "params": [{"name": "self", "type": null, "default": null}], "returns": {"name": "None", "xref": {"fqname": "constants.None", "project": "--std--"}, "params": null}, "documentation": []}, {"name": "daiquiri.tests.test_formatter.TestColorExtrasFormatter.test_no_keywords", "asynchronous": false, "params": [{"name": "self", "type": null, "default": null}], "returns": {"name": "None", "xref": {"fqname": "constants.None", "project": "--std--"}, "params": null}, "documentation": []}, {"name": "daiquiri.tests.test_formatter.TestColorExtrasFormatter.test_no_keywords_with_extras", "asynchronous": false, "params": [{"name": "self", "type": null, "default": null}], "returns": {"name": "None", "xref": {"fqname": "constants.None", "project": "--std--"}, "params": null}, "documentation": []}, {"name": "daiquiri.tests.test_formatter.TestColorExtrasFormatter.test_empty_keywords", "asynchronous": false, "params": [{"name": "self", "type": null, "default": null}], "returns": {"name": "None", "xref": {"fqname": "constants.None", "project": "--std--"}, "params": null}, "documentation": []}, {"name": "daiquiri.tests.test_formatter.TestColorExtrasFormatter.test_keywords_no_extras", "asynchronous": false, "params": [{"name": "self", "type": null, "default": null}], "returns": {"name": "None", "xref": {"fqname": "constants.None", "project": "--std--"}, "params": null}, "documentation": []}, {"name": "daiquiri.tests.test_formatter.TestColorExtrasFormatter.test_keywords_with_extras", "asynchronous": false, "params": [{"name": "self", "type": null, "default": null}], "returns": {"name": "None", "xref": {"fqname": "constants.None", "project": "--std--"}, "params": null}, "documentation": []}], "class_variables": [{"name": "daiquiri.tests.test_formatter.TestColorExtrasFormatter.logger", "type": {"name": "daiquiri.KeywordArgumentAdapter", "xref": {"fqname": "daiquiri.KeywordArgumentAdapter", "project": null}, "params": null}, "documentation": []}, {"name": "daiquiri.tests.test_formatter.TestColorExtrasFormatter.stream", "type": {"name": "io.StringIO", "xref": {"fqname": "io.StringIO", "project": "--std--"}, "params": null}, "documentation": []}, {"name": "daiquiri.tests.test_formatter.TestColorExtrasFormatter.handler", "type": {"name": "daiquiri.handlers.TTYDetectorStreamHandler", "xref": {"fqname": "daiquiri.handlers.TTYDetectorStreamHandler", "project": null}, "params": null}, "documentation": []}], "instance_variables": [], "inner_classes": [], "documentation": []}], "exports": []}, {"name": "daiquiri.tests.test_output", "documentation": ["Licensed under the Apache License, Version 2.0 (the \"License\"); you may", "not use this file except in compliance with the License. You may obtain", "a copy of the License at", "http://www.apache.org/licenses/LICENSE-2.0", "Unless required by applicable law or agreed to in writing, software", "distributed under the License is distributed on an \"AS IS\" BASIS, WITHOUT", "WARRANTIES OR CONDITIONS OF ANY KIND, either express or implied. See the", "License for the specific language governing permissions and limitations", "under the License."], "functions": [], "variables": [], "classes": [{"name": "daiquiri.tests.test_output.DatadogMatcher", "bases": ["object"], "methods": [{"name": "daiquiri.tests.test_output.DatadogMatcher.__init__", "asynchronous": false, "params": [{"name": "self", "type": null, "default": null}, {"name": "expected", "type": {"name": "typing.Any", "xref": {"fqname": "typing.Any", "project": "--std--"}, "params": null}, "default": null}], "returns": {"name": "None", "xref": {"fqname": "constants.None", "project": "--std--"}, "params": null}, "documentation": []}, {"name": "daiquiri.tests.test_output.DatadogMatcher.__eq__", "asynchronous": false, "params": [{"name": "self", "type": null, "default": null}, {"name": "other", "type": {"name": "typing.Any", "xref": {"fqname": "typing.Any", "project": "--std--"}, "params": null}, "default": null}], "returns": {"name": "bool", "xref": {"fqname": "functions.bool", "project": "--std--"}, "params": null}, "documentation": []}, {"name": "daiquiri.tests.test_output.DatadogMatcher.__repr__", "asynchronous": false, "params": [{"name": "self", "type": null, "default": null}], "returns": {"name": "str", "xref": {"fqname": "functions.str", "project": "--std--"}, "params": null}, "documentation": []}], "class_variables": [], "instance_variables": [], "inner_classes": [], "documentation": []}, {"name": "daiquiri.tests.test_output.TestOutput", "bases": ["unittest.TestCase"], "methods": [{"name": "daiquiri.tests.test_output.TestOutput.test_find_facility", "asynchronous": false, "params": [{"name": "self", "type": null, "default": null}], "returns": {"name": "None", "xref": {"fqname": "constants.None", "project": "--std--"}, "params": null}, "documentation": []}, {"name": "daiquiri.tests.test_output.TestOutput.test_get_log_file_path", "asynchronous": false, "params": [{"name": "self", "type": null, "default": null}], "returns": {"name": "None", "xref": {"fqname": "constants.None", "project": "--std--"}, "params": null}, "documentation": []}, {"name": "daiquiri.tests.test_output.TestOutput.test_timedelta_seconds", "asynchronous": false, "params": [{"name": "self", "type": null, "default": null}], "returns": {"name": "None", "xref": {"fqname": "constants.None", "project": "--std--"}, "params": null}, "documentation": []}, {"name": "daiquiri.tests.test_output.TestOutput.test_datadog", "asynchronous": false, "params": [{"name": "self", "type": null, "default": null}], "returns": {"name": "None", "xref": {"fqname": "constants.None", "project": "--std--"}, "params": null}, "documentation": []}], "class_variables": [], "instance_variables": [], "inner_classes": [], "documentation": []}], "exports": []}, {"name": "daiquiri.tests.test_daiquiri", "documentation": ["Licensed under the Apache License, Version 2.0 (the \"License\"); you may", "not use this file except in compliance with the License. You may obtain", "a copy of the License at", "http://www.apache.org/licenses/LICENSE-2.0", "Unless required by applicable law or agreed to in writing, software", "distributed under the License is distributed on an \"AS IS\" BASIS, WITHOUT", "WARRANTIES OR CONDITIONS OF ANY KIND, either express or implied. See the", "License for the specific language governing permissions and limitations", "under the License."], "functions": [{"name": "daiquiri.tests.test_daiquiri.test_extra_with_two_loggers", "asynchronous": false, "params": [], "returns": {"name": "None", "xref": {"fqname": "constants.None", "project": "--std--"}, "params": null}, "documentation": []}], "variables": [], "classes": [{"name": "daiquiri.tests.test_daiquiri.TestDaiquiri", "bases": ["unittest.TestCase"], "methods": [{"name": "daiquiri.tests.test_daiquiri.TestDaiquiri.tearDown", "asynchronous": false, "params": [{"name": "self", "type": null, "default": null}], "returns": {"name": "None", "xref": {"fqname": "constants.None", "project": "--std--"}, "params": null}, "documentation": []}, {"name": "daiquiri.tests.test_daiquiri.TestDaiquiri.test_setup", "asynchronous": false, "params": [{"name": "self", "type": null, "default": null}], "returns": {"name": "None", "xref": {"fqname": "constants.None", "project": "--std--"}, "params": null}, "documentation": []}, {"name": "daiquiri.tests.test_daiquiri.TestDaiquiri.test_setup_json_formatter", "asynchronous": false, "params": [{"name": "self", "type": null, "default": null}], "returns": {"name": "None", "xref": {"fqname": "constants.None", "project": "--std--"}, "params": null}, "documentation": []}, {"name": "daiquiri.tests.test_daiquiri.TestDaiquiri.test_setup_json_formatter_with_extras", "asynchronous": false, "params": [{"name": "self", "type": null, "default": null}], "returns": {"name": "None", "xref": {"fqname": "constants.None", "project": "--std--"}, "params": null}, "documentation": []}, {"name": "daiquiri.tests.test_daiquiri.TestDaiquiri.test_get_logger_set_level", "asynchronous": false, "params": [{"name": "self", "type": null, "default": null}], "returns": {"name": "None", "xref": {"fqname": "constants.None", "project": "--std--"}, "params": null}, "documentation": []}, {"name": "daiquiri.tests.test_daiquiri.TestDaiquiri.test_capture_warnings", "asynchronous": false, "params": [{"name": "self", "type": null, "default": null}], "returns": {"name": "None", "xref": {"fqname": "constants.None", "project": "--std--"}, "params": null}, "documentation": []}, {"name": "daiquiri.tests.test_daiquiri.TestDaiquiri.test_no_capture_warnings", "asynchronous": false, "params": [{"name": "self", "type": null, "default": null}], "returns": {"name": "None", "xref": {"fqname": "constants.None", "project": "--std--"}, "params": null}, "documentation": []}, {"name": "daiquiri.tests.test_daiquiri.TestDaiquiri.test_set_default_log_levels", "asynchronous": false, "params": [{"name": "self", "type": null, "default": null}], "returns": {"name": "None", "xref": {"fqname": "constants.None", "project": "--std--"}, "params": null}, "documentation": []}, {"name": "daiquiri.tests.test_daiquiri.TestDaiquiri.test_parse_and_set_default_log_levels", "asynchronous": false, "params": [{"name": "self", "type": null, "default": null}], "returns": {"name": "None", "xref": {"fqname": "constants.None", "project": "--std--"}, "params": null}, "documentation": []}, {"name": "daiquiri.tests.test_daiquiri.TestDaiquiri.test_string_as_setup_outputs_arg", "asynchronous": false, "params": [{"name": "self", "type": null, "default": null}], "returns": {"name": "None", "xref": {"fqname": "constants.None", "project": "--std--"}, "params": null}, "documentation": []}, {"name": "daiquiri.tests.test_daiquiri.TestDaiquiri.test_special_kwargs", "asynchronous": false, "params": [{"name": "self", "type": null, "default": null}], "returns": {"name": "None", "xref": {"fqname": "constants.None", "project": "--std--"}, "params": null}, "documentation": []}], "class_variables": [], "instance_variables": [], "inner_classes": [], "documentation": []}], "exports": []}, {"name": "daiquiri.types", "documentation": ["flake8: noqa: A005"], "functions": [], "variables": [], "classes": [{"name": "daiquiri.types.ColoredLogRecord", "bases": ["logging.LogRecord"], "methods": [], "class_variables": [{"name": "daiquiri.types.ColoredLogRecord.color", "type": {"name": "str", "xref": {"fqname": "functions.str", "project": "--std--"}, "params": null}, "documentation": []}, {"name": "daiquiri.types.ColoredLogRecord.color_stop", "type": {"name": "str", "xref": {"fqname": "functions.str", "project": "--std--"}, "params": null}, "documentation": []}], "instance_variables": [], "inner_classes": [], "documentation": []}, {"name": "daiquiri.types.ExtrasLogRecord", "bases": ["logging.LogRecord"], "methods": [], "class_variables": [{"name": "daiquiri.types.ExtrasLogRecord.extras_prefix", "type": {"name": "str", "xref": {"fqname": "functions.str", "project": "--std--"}, "params": null}, "documentation": []}, {"name": "daiquiri.types.ExtrasLogRecord.extras_suffix", "type": {"name": "str", "xref": {"fqname": "functions.str", "project": "--std--"}, "params": null}, "documentation": []}, {"name": "daiquiri.types.ExtrasLogRecord.extras", "type": {"name": "str", "xref": {"fqname": "functions.str", "project": "--std--"}, "params": null}, "documentation": []}, {"name": "daiquiri.types.ExtrasLogRecord._daiquiri_extra_keys", "type": {"name": "typing.Set", "xref": {"fqname": "typing.Set", "project": "--std--"}, "params": [{"name": "str", "xref": {"fqname": "functions.str", "project": "--std--"}, "params": null}]}, "documentation": []}], "instance_variables": [], "inner_classes": [], "documentation": []}, {"name": "daiquiri.types.TTYDetectionLogRecord", "bases": ["logging.LogRecord"], "methods": [], "class_variables": [{"name": "daiquiri.types.TTYDetectionLogRecord._stream_is_a_tty", "type": {"name": "bool", "xref": {"fqname": "functions.bool", "project": "--std--"}, "params": null}, "documentation": []}], "instance_variables": [], "inner_classes": [], "documentation": []}], "exports": []}, {"name": "daiquiri.handlers", "documentation": ["-*- coding: utf-8 -*-", "Licensed under the Apache License, Version 2.0 (the \"License\"); you may", "not use this file except in compliance with the License. You may obtain", "a copy of the License at", "http://www.apache.org/licenses/LICENSE-2.0", "Unless required by applicable law or agreed to in writing, software", "distributed under the License is distributed on an \"AS IS\" BASIS, WITHOUT", "WARRANTIES OR CONDITIONS OF ANY KIND, either express or implied. See the", "License for the specific language governing permissions and limitations", "under the License."], "functions": [], "variables": [{"name": "daiquiri.handlers.journal", "type": null, "documentation": []}, {"name": "daiquiri.handlers.syslog", "type": null, "documentation": ["type: ignore[assignment]"]}, {"name": "daiquiri.handlers.SYSLOG_MAP", "type": null, "documentation": []}, {"name": "daiquiri.handlers._TTYDetectorStreamHandlerBase", "type": null, "documentation": []}, {"name": "daiquiri.handlers._TTYDetectorStreamHandlerBase", "type": null, "documentation": []}], "classes": [{"name": "daiquiri.handlers.SyslogHandler", "bases": ["logging.Handler"], "methods": [{"name": "daiquiri.handlers.SyslogHandler.__init__", "asynchronous": false, "params": [{"name": "self", "type": null, "default": null}, {"name": "program_name", "type": {"name": "str", "xref": {"fqname": "functions.str", "project": "--std--"}, "params": null}, "default": null}, {"name": "facility", "type": {"name": "typing.Optional", "xref": {"fqname": "typing.Optional", "project": "--std--"}, "params": [{"name": "int", "xref": {"fqname": "functions.int", "project": "--std--"}, "params": null}]}, "default": "..."}], "returns": {"name": "None", "xref": {"fqname": "constants.None", "project": "--std--"}, "params": null}, "documentation": []}, {"name": "daiquiri.handlers.SyslogHandler.emit", "asynchronous": false, "params": [{"name": "self", "type": null, "default": null}, {"name": "record", "type": {"name": "logging.LogRecord", "xref": {"fqname": "logging.LogRecord", "project": "--std--"}, "params": null}, "default": null}], "returns": {"name": "None", "xref": {"fqname": "constants.None", "project": "--std--"}, "params": null}, "documentation": []}], "class_variables": [], "instance_variables": [], "inner_classes": [], "documentation": ["Syslog based handler. Only available on UNIX-like platforms."]}, {"name": "daiquiri.handlers.JournalHandler", "bases": ["logging.Handler"], "methods": [{"name": "daiquiri.handlers.JournalHandler.__init__", "asynchronous": false, "params": [{"name": "self", "type": null, "default": null}, {"name": "program_name", "type": {"name": "str", "xref": {"fqname": "functions.str", "project": "--std--"}, "params": null}, "default": null}], "returns": {"name": "None", "xref": {"fqname": "constants.None", "project": "--std--"}, "params": null}, "documentation": []}, {"name": "daiquiri.handlers.JournalHandler.emit", "asynchronous": false, "params": [{"name": "self", "type": null, "default": null}, {"name": "record", "type": {"name": "logging.LogRecord", "xref": {"fqname": "logging.LogRecord", "project": "--std--"}, "params": null}, "default": null}], "returns": {"name": "None", "xref": {"fqname": "constants.None", "project": "--std--"}, "params": null}, "documentation": []}], "class_variables": [{"name": "daiquiri.handlers.JournalHandler.program_name", "type": {"name": "str", "xref": {"fqname": "functions.str", "project": "--std--"}, "params": null}, "documentation": []}], "instance_variables": [], "inner_classes": [], "documentation": ["Journald based handler. Only available on platforms using systemd."]}, {"name": "daiquiri.handlers.TTYDetectorStreamHandler", "bases": ["_TTYDetectorStreamHandlerBase"], "methods": [{"name": "daiquiri.handlers.TTYDetectorStreamHandler.format", "asynchronous": false, "params": [{"name": "self", "type": null, "default": null}, {"name": "record", "type": {"name": "logging.LogRecord", "xref": {"fqname": "logging.LogRecord", "project": "--std--"}, "params": null}, "default": null}], "returns": {"name": "str", "xref": {"fqname": "functions.str", "project": "--std--"}, "params": null}, "documentation": []}], "class_variables": [], "instance_variables": [], "inner_classes": [], "documentation": ["Stream handler that adds a hint in the record if the stream is a TTY."]}, {"name": "daiquiri.handlers.PlainTextSocketHandler", "bases": ["logging.handlers.SocketHandler"], "methods": [{"name": "daiquiri.handlers.PlainTextSocketHandler.__init__", "asynchronous": false, "params": [{"name": "self", "type": null, "default": null}, {"name": "hostname", "type": {"name": "str", "xref": {"fqname": "functions.str", "project": "--std--"}, "params": null}, "default": null}, {"name": "port", "type": {"name": "int", "xref": {"fqname": "functions.int", "project": "--std--"}, "params": null}, "default": null}, {"name": "encoding", "type": {"name": "str", "xref": {"fqname": "functions.str", "project": "--std--"}, "params": null}, "default": "..."}], "returns": {"name": "None", "xref": {"fqname": "constants.None", "project": "--std--"}, "params": null}, "documentation": []}, {"name": "daiquiri.handlers.PlainTextSocketHandler.makePickle", "asynchronous": false, "params": [{"name": "self", "type": null, "default": null}, {"name": "record", "type": {"name": "logging.LogRecord", "xref": {"fqname": "logging.LogRecord", "project": "--std--"}, "params": null}, "default": null}], "returns": {"name": "bytes", "xref": {"fqname": "functions.bytes", "project": "--std--"}, "params": null}, "documentation": []}], "class_variables": [], "instance_variables": [], "inner_classes": [], "documentation": ["Socket handler that uses format and encode the record."]}, {"name": "daiquiri.handlers.PlainTextDatagramHandler", "bases": ["logging.handlers.DatagramHandler"], "methods": [{"name": "daiquiri.handlers.PlainTextDatagramHandler.__init__", "asynchronous": false, "params": [{"name": "self", "type": null, "default": null}, {"name": "hostname", "type": {"name": "str", "xref": {"fqname": "functions.str", "project": "--std--"}, "params": null}, "default": null}, {"name": "port", "type": {"name": "int", "xref": {"fqname": "functions.int", "project": "--std--"}, "params": null}, "default": null}, {"name": "encoding", "type": {"name": "str", "xref": {"fqname": "functions.str", "project": "--std--"}, "params": null}, "default": "..."}], "returns": {"name": "None", "xref": {"fqname": "constants.None", "project": "--std--"}, "params": null}, "documentation": []}, {"name": "daiquiri.handlers.PlainTextDatagramHandler.makePickle", "asynchronous": false, "params": [{"name": "self", "type": null, "default": null}, {"name": "record", "type": {"name": "logging.LogRecord", "xref": {"fqname": "logging.LogRecord", "project": "--std--"}, "params": null}, "default": null}], "returns": {"name": "bytes", "xref": {"fqname": "functions.bytes", "project": "--std--"}, "params": null}, "documentation": []}], "class_variables": [], "instance_variables": [], "inner_classes": [], "documentation": ["Socket handler that uses format and encode the record."]}], "exports": []}, {"name": "daiquiri", "documentation": ["Licensed under the Apache License, Version 2.0 (the \"License\"); you may", "not use this file except in compliance with the License. You may obtain", "a copy of the License at", "http://www.apache.org/licenses/LICENSE-2.0", "Unless required by applicable law or agreed to in writing, software", "distributed under the License is distributed on an \"AS IS\" BASIS, WITHOUT", "WARRANTIES OR CONDITIONS OF ANY KIND, either express or implied. See the", "License for the specific language governing permissions and limitations", "under the License."], "functions": [{"name": "daiquiri.getLogger", "asynchronous": false, "params": [{"name": "name", "type": {"name": "typing.Optional", "xref": {"fqname": "typing.Optional", "project": "--std--"}, "params": [{"name": "str", "xref": {"fqname": "functions.str", "project": "--std--"}, "params": null}]}, "default": "..."}, {"name": "**kwargs", "type": {"name": "typing.Any", "xref": {"fqname": "typing.Any", "project": "--std--"}, "params": null}, "default": null}], "returns": {"name": "KeywordArgumentAdapter", "xref": {"fqname": "daiquiri.KeywordArgumentAdapter", "project": null}, "params": null}, "documentation": ["Build a logger with the given name.\n\n```\nparam name\n\nThe name for the logger. This is usually the module\nname, __name__.\n\ntype name\n\nstring\n```\n"]}, {"name": "daiquiri.setup", "asynchronous": false, "params": [{"name": "level", "type": {"name": "typing.Union", "xref": {"fqname": "typing.Union", "project": "--std--"}, "params": [{"name": "int", "xref": {"fqname": "functions.int", "project": "--std--"}, "params": null}, {"name": "str", "xref": {"fqname": "functions.str", "project": "--std--"}, "params": null}]}, "default": "..."}, {"name": "outputs", "type": {"name": "typing.Iterable", "xref": {"fqname": "typing.Iterable", "project": "--std--"}, "params": [{"name": "typing.Union", "xref": {"fqname": "typing.Union", "project": "--std--"}, "params": [{"name": "output.Output", "xref": {"fqname": "daiquiri.output.Output", "project": null}, "params": null}, {"name": "str", "xref": {"fqname": "functions.str", "project": "--std--"}, "params": null}]}]}, "default": "..."}, {"name": "program_name", "type": {"name": "typing.Optional", "xref": {"fqname": "typing.Optional", "project": "--std--"}, "params": [{"name": "str", "xref": {"fqname": "functions.str", "project": "--std--"}, "params": null}]}, "default": "..."}, {"name": "capture_warnings", "type": {"name": "bool", "xref": {"fqname": "functions.bool", "project": "--std--"}, "params": null}, "default": "..."}, {"name": "set_excepthook", "type": {"name": "bool", "xref": {"fqname": "functions.bool", "project": "--std--"}, "params": null}, "default": "..."}], "returns": {"name": "None", "xref": {"fqname": "constants.None", "project": "--std--"}, "params": null}, "documentation": ["Set up Python logging.\n\nThis sets up basic handlers for Python logging.\n\n```\nparam level\n\nRoot log level.\n\nparam outputs\n\nIterable of outputs to log to.\n\nparam program_name\n\nThe name of the program. Auto-detected if not set.\n\nparam capture_warnings\n\nCapture warnings from the  module.\n```\n"]}, {"name": "daiquiri.parse_and_set_default_log_levels", "asynchronous": false, "params": [{"name": "default_log_levels", "type": {"name": "typing.Iterable", "xref": {"fqname": "typing.Iterable", "project": "--std--"}, "params": [{"name": "str", "xref": {"fqname": "functions.str", "project": "--std--"}, "params": null}]}, "default": null}, {"name": "separator", "type": {"name": "str", "xref": {"fqname": "functions.str", "project": "--std--"}, "params": null}, "default": "..."}], "returns": {"name": "None", "xref": {"fqname": "constants.None", "project": "--std--"}, "params": null}, "documentation": ["Set default log levels for some loggers.\n\n```\nparam default_log_levels\n\nList of strings with format\n<logger_name><separator><log_level>\n```\n"]}, {"name": "daiquiri.set_default_log_levels", "asynchronous": false, "params": [{"name": "loggers_and_log_levels", "type": {"name": "typing.Iterable", "xref": {"fqname": "typing.Iterable", "project": "--std--"}, "params": [{"name": "typing.Tuple", "xref": {"fqname": "typing.Tuple", "project": "--std--"}, "params": [{"name": "typing.Optional", "xref": {"fqname": "typing.Optional", "project": "--std--"}, "params": [{"name": "str", "xref": {"fqname": "functions.str", "project": "--std--"}, "params": null}]}, {"name": "typing.Union", "xref": {"fqname": "typing.Union", "project": "--std--"}, "params": [{"name": "str", "xref": {"fqname": "functions.str", "project": "--std--"}, "params": null}, {"name": "int", "xref": {"fqname": "functions.int", "project": "--std--"}, "params": null}]}]}]}, "default": null}], "returns": {"name": "None", "xref": {"fqname": "constants.None", "project": "--std--"}, "params": null}, "documentation": ["Set default log levels for some loggers.\n\n```\nparam loggers_and_log_levels\n\nList of tuple (logger name, level).\n```\n"]}], "variables": [{"name": "daiquiri._KeywordArgumentAdapterBase", "type": null, "documentation": []}, {"name": "daiquiri._KeywordArgumentAdapterBase", "type": null, "documentation": []}], "classes": [{"name": "daiquiri.KeywordArgumentAdapter", "bases": ["_KeywordArgumentAdapterBase"], "methods": [{"name": "daiquiri.KeywordArgumentAdapter.process", "asynchronous": false, "params": [{"name": "self", "type": null, "default": null}, {"name": "msg", "type": {"name": "typing.Any", "xref": {"fqname": "typing.Any", "project": "--std--"}, "params": null}, "default": null}, {"name": "kwargs", "type": {"name": "collections.abc.MutableMapping", "xref": {"fqname": "collections.abc.MutableMapping", "project": "--std--"}, "params": [{"name": "str", "xref": {"fqname": "functions.str", "project": "--std--"}, "params": null}, {"name": "typing.Any", "xref": {"fqname": "typing.Any", "project": "--std--"}, "params": null}]}, "default": null}], "returns": {"name": "typing.Tuple", "xref": {"fqname": "typing.Tuple", "project": "--std--"}, "params": [{"name": "typing.Any", "xref": {"fqname": "typing.Any", "project": "--std--"}, "params": null}, {"name": "collections.abc.MutableMapping", "xref": {"fqname": "collections.abc.MutableMapping", "project": "--std--"}, "params": [{"name": "str", "xref": {"fqname": "functions.str", "project": "--std--"}, "params": null}, {"name": "typing.Any", "xref": {"fqname": "typing.Any", "project": "--std--"}, "params": null}]}]}, "documentation": []}], "class_variables": [], "instance_variables": [], "inner_classes": [], "documentation": ["Logger adapter to add keyword arguments to log record's extra data.\n\nKeywords passed to the log call are added to the \"extra\"\ndictionary passed to the underlying logger so they are emitted\nwith the log message and available to the format string.\n\nSpecial keywords:\n\nextra\n  An existing dictionary of extra values to be passed to the\n  logger. If present, the dictionary is copied and extended."]}], "exports": [{"name": "daiquiri.output", "xref": {"fqname": "daiquiri.output", "project": null}}]}, {"name": "daiquiri.output", "documentation": ["Licensed under the Apache License, Version 2.0 (the \"License\"); you may", "not use this file except in compliance with the License. You may obtain", "a copy of the License at", "http://www.apache.org/licenses/LICENSE-2.0", "Unless required by applicable law or agreed to in writing, software", "distributed under the License is distributed on an \"AS IS\" BASIS, WITHOUT", "WARRANTIES OR CONDITIONS OF ANY KIND, either express or implied. See the", "License for the specific language governing permissions and limitations", "under the License."], "functions": [{"name": "daiquiri.output.get_program_name", "asynchronous": false, "params": [], "returns": {"name": "str", "xref": {"fqname": "functions.str", "project": "--std--"}, "params": null}, "documentation": ["Return the name of the running program."]}, {"name": "daiquiri.output._get_log_file_path", "asynchronous": false, "params": [{"name": "logfile", "type": {"name": "typing.Optional", "xref": {"fqname": "typing.Optional", "project": "--std--"}, "params": [{"name": "str", "xref": {"fqname": "functions.str", "project": "--std--"}, "params": null}]}, "default": "..."}, {"name": "logdir", "type": {"name": "typing.Optional", "xref": {"fqname": "typing.Optional", "project": "--std--"}, "params": [{"name": "str", "xref": {"fqname": "functions.str", "project": "--std--"}, "params": null}]}, "default": "..."}, {"name": "program_name", "type": {"name": "typing.Optional", "xref": {"fqname": "typing.Optional", "project": "--std--"}, "params": [{"name": "str", "xref": {"fqname": "functions.str", "project": "--std--"}, "params": null}]}, "default": "..."}, {"name": "logfile_suffix", "type": {"name": "str", "xref": {"fqname": "functions.str", "project": "--std--"}, "params": null}, "default": "..."}], "returns": {"name": "str", "xref": {"fqname": "functions.str", "project": "--std--"}, "params": null}, "documentation": []}], "variables": [{"name": "daiquiri.output.syslog", "type": null, "documentation": ["type: ignore[assignment]"]}, {"name": "daiquiri.output.STDERR", "type": null, "documentation": []}, {"name": "daiquiri.output.STDOUT", "type": null, "documentation": []}, {"name": "daiquiri.output.preconfigured", "type": {"name": "typing.Dict", "xref": {"fqname": "typing.Dict", "project": "--std--"}, "params": [{"name": "str", "xref": {"fqname": "functions.str", "project": "--std--"}, "params": null}, {"name": "typing.Union", "xref": {"fqname": "typing.Union", "project": "--std--"}, "params": [{"name": "Stream", "xref": {"fqname": "daiquiri.output.Stream", "project": null}, "params": null}, {"name": "Output", "xref": {"fqname": "daiquiri.output.Output", "project": null}, "params": null}]}]}, "documentation": []}], "classes": [{"name": "daiquiri.output.Output", "bases": [], "methods": [{"name": "daiquiri.output.Output.__init__", "asynchronous": false, "params": [{"name": "self", "type": null, "default": null}, {"name": "handler", "type": {"name": "logging.Handler", "xref": {"fqname": "logging.Handler", "project": "--std--"}, "params": null}, "default": null}, {"name": "formatter", "type": {"name": "logging.Formatter", "xref": {"fqname": "logging.Formatter", "project": "--std--"}, "params": null}, "default": "..."}, {"name": "level", "type": {"name": "typing.Optional", "xref": {"fqname": "typing.Optional", "project": "--std--"}, "params": [{"name": "int", "xref": {"fqname": "functions.int", "project": "--std--"}, "params": null}]}, "default": "..."}], "returns": null, "documentation": []}, {"name": "daiquiri.output.Output.add_to_logger", "asynchronous": false, "params": [{"name": "self", "type": null, "default": null}, {"name": "logger", "type": {"name": "logging.Logger", "xref": {"fqname": "logging.Logger", "project": "--std--"}, "params": null}, "default": null}], "returns": {"name": "None", "xref": {"fqname": "constants.None", "project": "--std--"}, "params": null}, "documentation": ["Add this output to a logger."]}], "class_variables": [], "instance_variables": [], "inner_classes": [], "documentation": ["Generic log output."]}, {"name": "daiquiri.output.File", "bases": ["Output"], "methods": [{"name": "daiquiri.output.File.__init__", "asynchronous": false, "params": [{"name": "self", "type": null, "default": null}, {"name": "filename", "type": {"name": "typing.Optional", "xref": {"fqname": "typing.Optional", "project": "--std--"}, "params": [{"name": "str", "xref": {"fqname": "functions.str", "project": "--std--"}, "params": null}]}, "default": "..."}, {"name": "directory", "type": {"name": "typing.Optional", "xref": {"fqname": "typing.Optional", "project": "--std--"}, "params": [{"name": "str", "xref": {"fqname": "functions.str", "project": "--std--"}, "params": null}]}, "default": "..."}, {"name": "suffix", "type": {"name": "str", "xref": {"fqname": "functions.str", "project": "--std--"}, "params": null}, "default": "..."}, {"name": "program_name", "type": {"name": "typing.Optional", "xref": {"fqname": "typing.Optional", "project": "--std--"}, "params": [{"name": "str", "xref": {"fqname": "functions.str", "project": "--std--"}, "params": null}]}, "default": "..."}, {"name": "formatter", "type": {"name": "logging.Formatter", "xref": {"fqname": "logging.Formatter", "project": "--std--"}, "params": null}, "default": "..."}, {"name": "level", "type": {"name": "typing.Optional", "xref": {"fqname": "typing.Optional", "project": "--std--"}, "params": [{"name": "int", "xref": {"fqname": "functions.int", "project": "--std--"}, "params": null}]}, "default": "..."}], "returns": null, "documentation": ["Log file output.\n\n```\nparam filename\n\nThe log file path to write to. If directory is also\nspecified, both will be combined.\n\nparam directory\n\nThe log directory to write to. If no filename is\nspecified, the program name and suffix will be used\nto contruct the full path relative to the directory.\n\nparam suffix\n\nThe log file name suffix. This will be only used if no\nfilename has been provided.\n\nparam program_name\n\nProgram name. Autodetected by default.\n```\n"]}], "class_variables": [], "instance_variables": [], "inner_classes": [], "documentation": ["Ouput to a file."]}, {"name": "daiquiri.output.RotatingFile", "bases": ["Output"], "methods": [{"name": "daiquiri.output.RotatingFile.__init__", "asynchronous": false, "params": [{"name": "self", "type": null, "default": null}, {"name": "filename", "type": {"name": "typing.Optional", "xref": {"fqname": "typing.Optional", "project": "--std--"}, "params": [{"name": "str", "xref": {"fqname": "functions.str", "project": "--std--"}, "params": null}]}, "default": "..."}, {"name": "directory", "type": {"name": "typing.Optional", "xref": {"fqname": "typing.Optional", "project": "--std--"}, "params": [{"name": "str", "xref": {"fqname": "functions.str", "project": "--std--"}, "params": null}]}, "default": "..."}, {"name": "suffix", "type": {"name": "str", "xref": {"fqname": "functions.str", "project": "--std--"}, "params": null}, "default": "..."}, {"name": "program_name", "type": {"name": "typing.Optional", "xref": {"fqname": "typing.Optional", "project": "--std--"}, "params": [{"name": "str", "xref": {"fqname": "functions.str", "project": "--std--"}, "params": null}]}, "default": "..."}, {"name": "formatter", "type": {"name": "logging.Formatter", "xref": {"fqname": "logging.Formatter", "project": "--std--"}, "params": null}, "default": "..."}, {"name": "level", "type": {"name": "typing.Optional", "xref": {"fqname": "typing.Optional", "project": "--std--"}, "params": [{"name": "int", "xref": {"fqname": "functions.int", "project": "--std--"}, "params": null}]}, "default": "..."}, {"name": "max_size_bytes", "type": {"name": "int", "xref": {"fqname": "functions.int", "project": "--std--"}, "params": null}, "default": "..."}, {"name": "backup_count", "type": {"name": "int", "xref": {"fqname": "functions.int", "project": "--std--"}, "params": null}, "default": "..."}], "returns": null, "documentation": ["Rotating log file output.\n\n```\nparam filename\n\nThe log file path to write to. If directory is also\nspecified, both will be combined.\n\nparam directory\n\nThe log directory to write to. If no filename is\nspecified, the program name and suffix will be used\nto contruct the full path relative to the directory.\n\nparam suffix\n\nThe log file name suffix. This will be only used if no\nfilename has been provided.\n\nparam program_name\n\nProgram name. Autodetected by default.\n\nparam max_size_bytes\n\nAllow the file to rollover at a predetermined\nsize.\n\nparam backup_count\n\nThe maximum number of files to rotate logging\noutput between.\n```\n"]}, {"name": "daiquiri.output.RotatingFile.do_rollover", "asynchronous": false, "params": [{"name": "self", "type": null, "default": null}], "returns": {"name": "None", "xref": {"fqname": "constants.None", "project": "--std--"}, "params": null}, "documentation": ["Manually forces a log file rotation."]}], "class_variables": [{"name": "daiquiri.output.RotatingFile.handler", "type": {"name": "logging.handlers.RotatingFileHandler", "xref": {"fqname": "logging.handlers.RotatingFileHandler", "project": "--std--"}, "params": null}, "documentation": []}], "instance_variables": [], "inner_classes": [], "documentation": ["Output to a file, rotating after a certain size."]}, {"name": "daiquiri.output.TimedRotatingFile", "bases": ["Output"], "methods": [{"name": "daiquiri.output.TimedRotatingFile.__init__", "asynchronous": false, "params": [{"name": "self", "type": null, "default": null}, {"name": "filename", "type": {"name": "typing.Optional", "xref": {"fqname": "typing.Optional", "project": "--std--"}, "params": [{"name": "str", "xref": {"fqname": "functions.str", "project": "--std--"}, "params": null}]}, "default": "..."}, {"name": "directory", "type": {"name": "typing.Optional", "xref": {"fqname": "typing.Optional", "project": "--std--"}, "params": [{"name": "str", "xref": {"fqname": "functions.str", "project": "--std--"}, "params": null}]}, "default": "..."}, {"name": "suffix", "type": {"name": "str", "xref": {"fqname": "functions.str", "project": "--std--"}, "params": null}, "default": "..."}, {"name": "program_name", "type": {"name": "typing.Optional", "xref": {"fqname": "typing.Optional", "project": "--std--"}, "params": [{"name": "str", "xref": {"fqname": "functions.str", "project": "--std--"}, "params": null}]}, "default": "..."}, {"name": "formatter", "type": {"name": "logging.Formatter", "xref": {"fqname": "logging.Formatter", "project": "--std--"}, "params": null}, "default": "..."}, {"name": "level", "type": {"name": "typing.Optional", "xref": {"fqname": "typing.Optional", "project": "--std--"}, "params": [{"name": "int", "xref": {"fqname": "functions.int", "project": "--std--"}, "params": null}]}, "default": "..."}, {"name": "interval", "type": {"name": "typing.Union", "xref": {"fqname": "typing.Union", "project": "--std--"}, "params": [{"name": "float", "xref": {"fqname": "functions.float", "project": "--std--"}, "params": null}, {"name": "int", "xref": {"fqname": "functions.int", "project": "--std--"}, "params": null}, {"name": "datetime.timedelta", "xref": {"fqname": "datetime.timedelta", "project": "--std--"}, "params": null}]}, "default": "..."}, {"name": "backup_count", "type": {"name": "int", "xref": {"fqname": "functions.int", "project": "--std--"}, "params": null}, "default": "..."}], "returns": null, "documentation": ["Rotating log file output, triggered by a fixed interval.\n\n```\nparam filename\n\nThe log file path to write to. If directory is also\nspecified, both will be combined.\n\nparam directory\n\nThe log directory to write to. If no filename is\nspecified, the program name and suffix will be used\nto contruct the full path relative to the directory.\n\nparam suffix\n\nThe log file name suffix. This will be only used if no\nfilename has been provided.\n\nparam program_name\n\nProgram name. Autodetected by default.\n\nparam interval\n\ndatetime.timedelta instance representing how often a\nnew log file should be created.\n\nparam backup_count\n\nThe maximum number of files to rotate logging\noutput between.\n```\n"]}, {"name": "daiquiri.output.TimedRotatingFile.do_rollover", "asynchronous": false, "params": [{"name": "self", "type": null, "default": null}], "returns": {"name": "None", "xref": {"fqname": "constants.None", "project": "--std--"}, "params": null}, "documentation": ["Manually forces a log file rotation."]}, {"name": "daiquiri.output.TimedRotatingFile._timedelta_to_seconds", "asynchronous": false, "params": [{"name": "td", "type": {"name": "typing.Union", "xref": {"fqname": "typing.Union", "project": "--std--"}, "params": [{"name": "float", "xref": {"fqname": "functions.float", "project": "--std--"}, "params": null}, {"name": "int", "xref": {"fqname": "functions.int", "project": "--std--"}, "params": null}, {"name": "datetime.timedelta", "xref": {"fqname": "datetime.timedelta", "project": "--std--"}, "params": null}]}, "default": null}], "returns": {"name": "float", "xref": {"fqname": "functions.float", "project": "--std--"}, "params": null}, "documentation": ["Convert a datetime.timedelta object into a seconds interval.\n\n```\nparam td\n\ndatetime.timedelta\n\nreturn\n\ntime in seconds\n\nrtype\n\nint\n```\n"]}], "class_variables": [{"name": "daiquiri.output.TimedRotatingFile.handler", "type": {"name": "logging.handlers.TimedRotatingFileHandler", "xref": {"fqname": "logging.handlers.TimedRotatingFileHandler", "project": "--std--"}, "params": null}, "documentation": []}], "instance_variables": [], "inner_classes": [], "documentation": ["Rotating log file output, triggered by a fixed interval."]}, {"name": "daiquiri.output.Stream", "bases": ["Output"], "methods": [{"name": "daiquiri.output.Stream.__init__", "asynchronous": false, "params": [{"name": "self", "type": null, "default": null}, {"name": "stream", "type": {"name": "typing.TextIO", "xref": {"fqname": "typing.TextIO", "project": "--std--"}, "params": null}, "default": "..."}, {"name": "formatter", "type": {"name": "logging.Formatter", "xref": {"fqname": "logging.Formatter", "project": "--std--"}, "params": null}, "default": "..."}, {"name": "level", "type": {"name": "typing.Optional", "xref": {"fqname": "typing.Optional", "project": "--std--"}, "params": [{"name": "int", "xref": {"fqname": "functions.int", "project": "--std--"}, "params": null}]}, "default": "..."}], "returns": {"name": "None", "xref": {"fqname": "constants.None", "project": "--std--"}, "params": null}, "documentation": []}], "class_variables": [], "instance_variables": [], "inner_classes": [], "documentation": ["Generic stream output."]}, {"name": "daiquiri.output.Journal", "bases": ["Output"], "methods": [{"name": "daiquiri.output.Journal.__init__", "asynchronous": false, "params": [{"name": "self", "type": null, "default": null}, {"name": "program_name", "type": {"name": "typing.Optional", "xref": {"fqname": "typing.Optional", "project": "--std--"}, "params": [{"name": "str", "xref": {"fqname": "functions.str", "project": "--std--"}, "params": null}]}, "default": "..."}, {"name": "formatter", "type": {"name": "logging.Formatter", "xref": {"fqname": "logging.Formatter", "project": "--std--"}, "params": null}, "default": "..."}, {"name": "level", "type": {"name": "typing.Optional", "xref": {"fqname": "typing.Optional", "project": "--std--"}, "params": [{"name": "int", "xref": {"fqname": "functions.int", "project": "--std--"}, "params": null}]}, "default": "..."}], "returns": {"name": "None", "xref": {"fqname": "constants.None", "project": "--std--"}, "params": null}, "documentation": []}], "class_variables": [], "instance_variables": [], "inner_classes": [], "documentation": []}, {"name": "daiquiri.output.Syslog", "bases": ["Output"], "methods": [{"name": "daiquiri.output.Syslog.__init__", "asynchronous": false, "params": [{"name": "self", "type": null, "default": null}, {"name": "program_name", "type": {"name": "typing.Optional", "xref": {"fqname": "typing.Optional", "project": "--std--"}, "params": [{"name": "str", "xref": {"fqname": "functions.str", "project": "--std--"}, "params": null}]}, "default": "..."}, {"name": "facility", "type": {"name": "str", "xref": {"fqname": "functions.str", "project": "--std--"}, "params": null}, "default": "..."}, {"name": "formatter", "type": {"name": "logging.Formatter", "xref": {"fqname": "logging.Formatter", "project": "--std--"}, "params": null}, "default": "..."}, {"name": "level", "type": {"name": "typing.Optional", "xref": {"fqname": "typing.Optional", "project": "--std--"}, "params": [{"name": "int", "xref": {"fqname": "functions.int", "project": "--std--"}, "params": null}]}, "default": "..."}], "returns": {"name": "None", "xref": {"fqname": "constants.None", "project": "--std--"}, "params": null}, "documentation": []}, {"name": "daiquiri.output.Syslog._find_facility", "asynchronous": false, "params": [{"name": "facility", "type": {"name": "str", "xref": {"fqname": "functions.str", "project": "--std--"}, "params": null}, "default": null}], "returns": {"name": "int", "xref": {"fqname": "functions.int", "project": "--std--"}, "params": null}, "documentation": []}], "class_variables": [], "instance_variables": [], "inner_classes": [], "documentation": []}, {"name": "daiquiri.output.Datadog", "bases": ["Output"], "methods": [{"name": "daiquiri.output.Datadog.__init__", "asynchronous": false, "params": [{"name": "self", "type": null, "default": null}, {"name": "hostname", "type": {"name": "str", "xref": {"fqname": "functions.str", "project": "--std--"}, "params": null}, "default": "..."}, {"name": "port", "type": {"name": "int", "xref": {"fqname": "functions.int", "project": "--std--"}, "params": null}, "default": "..."}, {"name": "formatter", "type": {"name": "logging.Formatter", "xref": {"fqname": "logging.Formatter", "project": "--std--"}, "params": null}, "default": "..."}, {"name": "level", "type": {"name": "typing.Optional", "xref": {"fqname": "typing.Optional", "project": "--std--"}, "params": [{"name": "int", "xref": {"fqname": "functions.int", "project": "--std--"}, "params": null}]}, "default": "..."}, {"name": "handler_class", "type": {"name": "typing.Type", "xref": {"fqname": "typing.Type", "project": "--std--"}, "params": [{"name": "logging.handlers.SocketHandler", "xref": {"fqname": "logging.handlers.SocketHandler", "project": "--std--"}, "params": null}]}, "default": "..."}], "returns": null, "documentation": []}], "class_variables": [], "instance_variables": [], "inner_classes": [], "documentation": []}], "exports": []}]}