{"name": "pathlib", "metadata": {"name": "pathlib", "version": "1.0.1", "classifiers": ["Development Status :: 5 - Production/Stable", "Intended Audience :: Developers", "License :: OSI Approved :: MIT License", "Operating System :: OS Independent", "Programming Language :: Python :: 2.6", "Programming Language :: Python :: 2.7", "Programming Language :: Python :: 3", "Programming Language :: Python :: 3.2", "Programming Language :: Python :: 3.3", "Programming Language :: Python :: 3.4", "Topic :: Software Development :: Libraries", "Topic :: System :: Filesystems"], "home_page": "https://pathlib.readthedocs.org/", "license": "MIT License", "documentation_url": null, "dependencies": [], "summary": "Object-oriented filesystem paths", "upload_time": 1651671440}, "documentation": ["**Attention:** this backport module isn't maintained anymore. If you want to report issues or contribute patches, please consider the [pathlib2](https://pypi.python.org/pypi/pathlib2/) project instead.\n\n# Description\n\npathlib offers a set of classes to handle filesystem paths. It offers the\nfollowing advantages over using string objects:\n\n- No more cumbersome use of os and os.path functions. Everything can be\n  done easily through operators, attribute accesses, and method calls.\n- Embodies the semantics of different path types. For example, comparing\n  Windows paths ignores casing.\n- Well-defined semantics, eliminating any warts or ambiguities (forward vs.\n  backward slashes, etc.).\n\n# Requirements\n\nPython 3.2 or later is recommended, but pathlib is also usable with Python 2.7\nand 2.6.\n\n# Install\n\nIn Python 3.4, pathlib is now part of the standard library. For Python 3.3\nand earlier, `easy_install pathlib` or `pip install pathlib` should do\nthe trick.\n\n# Examples\n\nImporting the module classes:\n\n```\n>>> from pathlib import *\n```\n\nListing Python source files in a directory:\n\n```\n>>> list(p.glob('*.py'))\n[PosixPath('test_pathlib.py'), PosixPath('setup.py'),\n PosixPath('pathlib.py')]\n```\n\nNavigating inside a directory tree:\n\n```\n>>> p = Path('/etc')\n>>> q = p / 'init.d' / 'reboot'\n>>> q\nPosixPath('/etc/init.d/reboot')\n>>> q.resolve()\nPosixPath('/etc/rc.d/init.d/halt')\n```\n\nQuerying path properties:\n\n```\n>>> q.exists()\nTrue\n>>> q.is_dir()\nFalse\n```\n\nOpening a file:\n\n```\n>>> with q.open() as f: f.readline()\n...\n'#!/bin/bash\\n'\n```\n\n# Documentation\n\nThe full documentation can be read at [Read the Docs](https://pathlib.readthedocs.org/).\n\n# Contributing\n\nMain development now takes place in the Python standard library: see\nthe [Python developer's guide](http://docs.python.org/devguide/), and\nreport issues on the [Python bug tracker](http://bugs.python.org/).\n\nHowever, if you find an issue specific to prior versions of Python\n(such as 2.7 or 3.2), you can post an issue on the\n[BitBucket project page](https://bitbucket.org/pitrou/pathlib/).\n\n# History\n\n## Version 1.0.1\n\n- Pull request #4: Python 2.6 compatibility by eevee.\n\n## Version 1.0\n\nThis version brings `pathlib` up to date with the official Python 3.4\nrelease, and also fixes a couple of 2.7-specific issues.\n\n- Python issue #20765: Add missing documentation for PurePath.with_name()\n  and PurePath.with_suffix().\n- Fix test_mkdir_parents when the working directory has additional bits\n  set (such as the setgid or sticky bits).\n- Python issue #20111: pathlib.Path.with_suffix() now sanity checks the\n  given suffix.\n- Python issue #19918: Fix PurePath.relative_to() under Windows.\n- Python issue #19921: When Path.mkdir() is called with parents=True, any\n  missing parent is created with the default permissions, ignoring the mode\n  argument (mimicking the POSIX \"mkdir -p\" command).\n- Python issue #19887: Improve the Path.resolve() algorithm to support\n  certain symlink chains.\n- Make pathlib usable under Python 2.7 with unicode pathnames (only pure\n  ASCII, though).\n- Issue #21: fix TypeError under Python 2.7 when using new division.\n- Add tox support for easier testing.\n\n## Version 0.97\n\nThis version brings `pathlib` up to date with the final API specified\nin {pep}`428`. The changes are too long to list here, it is recommended\nto read the [documentation](https://pathlib.readthedocs.org/).\n\n:::{warning}\nThe API in this version is partially incompatible with pathlib 0.8 and\nearlier. Be sure to check your code for possible breakage!\n:::\n\n## Version 0.8\n\n- Add PurePath.name and PurePath.anchor.\n- Add Path.owner and Path.group.\n- Add Path.replace().\n- Add Path.as_uri().\n- Issue #10: when creating a file with Path.open(), don't set the executable\n  bit.\n- Issue #11: fix comparisons with non-Path objects.\n\n## Version 0.7\n\n- Add '\\*\\*' (recursive) patterns to Path.glob().\n- Fix openat() support after the API refactoring in Python 3.3 beta1.\n- Add a *target_is_directory* argument to Path.symlink_to()\n\n## Version 0.6\n\n- Add Path.is_file() and Path.is_symlink()\n- Add Path.glob() and Path.rglob()\n- Add PurePath.match()\n\n## Version 0.5\n\n- Add Path.mkdir().\n- Add Python 2.7 compatibility by Michele Lacchia.\n- Make parent() raise ValueError when the level is greater than the path\n  length.\n"], "modules": [{"name": "pathlib", "documentation": [], "functions": [{"name": "pathlib._py2_fsencode", "asynchronous": false, "params": [{"name": "parts", "type": null, "default": null}], "returns": null, "documentation": []}, {"name": "pathlib._is_wildcard_pattern", "asynchronous": false, "params": [{"name": "pat", "type": null, "default": null}], "returns": null, "documentation": []}, {"name": "pathlib._cached", "asynchronous": false, "params": [{"name": "func", "type": null, "default": null}], "returns": null, "documentation": ["Globbing helpers"]}, {"name": "pathlib._make_selector", "asynchronous": false, "params": [{"name": "pattern_parts", "type": null, "default": null}], "returns": null, "documentation": []}], "variables": [{"name": "pathlib.intern", "type": null, "documentation": []}, {"name": "pathlib.intern", "type": null, "documentation": []}, {"name": "pathlib.basestring", "type": null, "documentation": []}, {"name": "pathlib.basestring", "type": null, "documentation": []}, {"name": "pathlib.supports_symlinks", "type": null, "documentation": []}, {"name": "pathlib.nt", "type": null, "documentation": []}, {"name": "pathlib.supports_symlinks", "type": null, "documentation": []}, {"name": "pathlib._getfinalpathname", "type": null, "documentation": []}, {"name": "pathlib._py2", "type": null, "documentation": []}, {"name": "pathlib._py2_fs_encoding", "type": null, "documentation": []}, {"name": "pathlib._windows_flavour", "type": null, "documentation": []}, {"name": "pathlib._posix_flavour", "type": null, "documentation": []}, {"name": "pathlib._normal_accessor", "type": null, "documentation": []}, {"name": "pathlib._make_selector", "type": null, "documentation": []}], "classes": [{"name": "pathlib._Flavour", "bases": ["object"], "methods": [{"name": "pathlib._Flavour.__init__", "asynchronous": false, "params": [{"name": "self", "type": null, "default": null}], "returns": null, "documentation": []}, {"name": "pathlib._Flavour.parse_parts", "asynchronous": false, "params": [{"name": "self", "type": null, "default": null}, {"name": "parts", "type": null, "default": null}], "returns": null, "documentation": []}, {"name": "pathlib._Flavour.join_parsed_parts", "asynchronous": false, "params": [{"name": "self", "type": null, "default": null}, {"name": "drv", "type": null, "default": null}, {"name": "root", "type": null, "default": null}, {"name": "parts", "type": null, "default": null}, {"name": "drv2", "type": null, "default": null}, {"name": "root2", "type": null, "default": null}, {"name": "parts2", "type": null, "default": null}], "returns": null, "documentation": ["Join the two paths represented by the respective\n(drive, root, parts) tuples.  Return a new (drive, root, parts) tuple."]}], "class_variables": [], "instance_variables": [], "inner_classes": [], "documentation": ["A flavour implements a particular (platform-specific) set of path\nsemantics."]}, {"name": "pathlib._WindowsFlavour", "bases": ["_Flavour"], "methods": [{"name": "pathlib._WindowsFlavour.splitroot", "asynchronous": false, "params": [{"name": "self", "type": null, "default": null}, {"name": "part", "type": null, "default": null}, {"name": "sep", "type": null, "default": "..."}], "returns": null, "documentation": ["Interesting findings about extended paths:", "- '\\\\?\\c:\\a', '//?/c:\\a' and '//?/c:/a' are all supported", "but '\\\\?\\c:/a' is not", "- extended paths are always absolute; \"relative\" extended paths will", "fail."]}, {"name": "pathlib._WindowsFlavour.casefold", "asynchronous": false, "params": [{"name": "self", "type": null, "default": null}, {"name": "s", "type": null, "default": null}], "returns": null, "documentation": []}, {"name": "pathlib._WindowsFlavour.casefold_parts", "asynchronous": false, "params": [{"name": "self", "type": null, "default": null}, {"name": "parts", "type": null, "default": null}], "returns": null, "documentation": []}, {"name": "pathlib._WindowsFlavour.resolve", "asynchronous": false, "params": [{"name": "self", "type": null, "default": null}, {"name": "path", "type": null, "default": null}], "returns": null, "documentation": []}, {"name": "pathlib._WindowsFlavour._split_extended_path", "asynchronous": false, "params": [{"name": "self", "type": null, "default": null}, {"name": "s", "type": null, "default": null}, {"name": "ext_prefix", "type": null, "default": "..."}], "returns": null, "documentation": []}, {"name": "pathlib._WindowsFlavour._ext_to_normal", "asynchronous": false, "params": [{"name": "self", "type": null, "default": null}, {"name": "s", "type": null, "default": null}], "returns": null, "documentation": []}, {"name": "pathlib._WindowsFlavour.is_reserved", "asynchronous": false, "params": [{"name": "self", "type": null, "default": null}, {"name": "parts", "type": null, "default": null}], "returns": null, "documentation": []}, {"name": "pathlib._WindowsFlavour.make_uri", "asynchronous": false, "params": [{"name": "self", "type": null, "default": null}, {"name": "path", "type": null, "default": null}], "returns": null, "documentation": []}], "class_variables": [{"name": "pathlib._WindowsFlavour.sep", "type": null, "documentation": []}, {"name": "pathlib._WindowsFlavour.altsep", "type": null, "documentation": []}, {"name": "pathlib._WindowsFlavour.has_drv", "type": null, "documentation": []}, {"name": "pathlib._WindowsFlavour.pathmod", "type": null, "documentation": []}, {"name": "pathlib._WindowsFlavour.is_supported", "type": null, "documentation": []}, {"name": "pathlib._WindowsFlavour.drive_letters", "type": null, "documentation": []}, {"name": "pathlib._WindowsFlavour.ext_namespace_prefix", "type": null, "documentation": []}, {"name": "pathlib._WindowsFlavour.reserved_names", "type": null, "documentation": []}], "instance_variables": [], "inner_classes": [], "documentation": []}, {"name": "pathlib._PosixFlavour", "bases": ["_Flavour"], "methods": [{"name": "pathlib._PosixFlavour.splitroot", "asynchronous": false, "params": [{"name": "self", "type": null, "default": null}, {"name": "part", "type": null, "default": null}, {"name": "sep", "type": null, "default": "..."}], "returns": null, "documentation": []}, {"name": "pathlib._PosixFlavour.casefold", "asynchronous": false, "params": [{"name": "self", "type": null, "default": null}, {"name": "s", "type": null, "default": null}], "returns": null, "documentation": []}, {"name": "pathlib._PosixFlavour.casefold_parts", "asynchronous": false, "params": [{"name": "self", "type": null, "default": null}, {"name": "parts", "type": null, "default": null}], "returns": null, "documentation": []}, {"name": "pathlib._PosixFlavour.resolve", "asynchronous": false, "params": [{"name": "self", "type": null, "default": null}, {"name": "path", "type": null, "default": null}], "returns": null, "documentation": []}, {"name": "pathlib._PosixFlavour.is_reserved", "asynchronous": false, "params": [{"name": "self", "type": null, "default": null}, {"name": "parts", "type": null, "default": null}], "returns": null, "documentation": []}, {"name": "pathlib._PosixFlavour.make_uri", "asynchronous": false, "params": [{"name": "self", "type": null, "default": null}, {"name": "path", "type": null, "default": null}], "returns": null, "documentation": []}], "class_variables": [{"name": "pathlib._PosixFlavour.sep", "type": null, "documentation": []}, {"name": "pathlib._PosixFlavour.altsep", "type": null, "documentation": []}, {"name": "pathlib._PosixFlavour.has_drv", "type": null, "documentation": []}, {"name": "pathlib._PosixFlavour.pathmod", "type": null, "documentation": []}, {"name": "pathlib._PosixFlavour.is_supported", "type": null, "documentation": []}], "instance_variables": [], "inner_classes": [], "documentation": []}, {"name": "pathlib._Accessor", "bases": [], "methods": [], "class_variables": [], "instance_variables": [], "inner_classes": [], "documentation": ["An accessor implements a particular (system-specific or not) way of\naccessing paths on the filesystem."]}, {"name": "pathlib._NormalAccessor", "bases": ["_Accessor"], "methods": [{"name": "pathlib._NormalAccessor._wrap_strfunc", "asynchronous": false, "params": [{"name": "strfunc", "type": null, "default": null}], "returns": null, "documentation": []}, {"name": "pathlib._NormalAccessor._wrap_binary_strfunc", "asynchronous": false, "params": [{"name": "strfunc", "type": null, "default": null}], "returns": null, "documentation": []}, {"name": "pathlib._NormalAccessor.lchmod", "asynchronous": false, "params": [{"name": "self", "type": null, "default": null}, {"name": "pathobj", "type": null, "default": null}, {"name": "mode", "type": null, "default": null}], "returns": null, "documentation": []}, {"name": "pathlib._NormalAccessor.symlink", "asynchronous": false, "params": [{"name": "a", "type": null, "default": null}, {"name": "b", "type": null, "default": null}, {"name": "target_is_directory", "type": null, "default": null}], "returns": null, "documentation": []}, {"name": "pathlib._NormalAccessor.symlink", "asynchronous": false, "params": [{"name": "a", "type": null, "default": null}, {"name": "b", "type": null, "default": null}, {"name": "target_is_directory", "type": null, "default": null}], "returns": null, "documentation": ["Under POSIX, os.symlink() takes two args"]}, {"name": "pathlib._NormalAccessor.readlink", "asynchronous": false, "params": [{"name": "self", "type": null, "default": null}, {"name": "path", "type": null, "default": null}], "returns": null, "documentation": ["Helper for resolve()"]}], "class_variables": [{"name": "pathlib._NormalAccessor.stat", "type": null, "documentation": []}, {"name": "pathlib._NormalAccessor.lstat", "type": null, "documentation": []}, {"name": "pathlib._NormalAccessor.open", "type": null, "documentation": []}, {"name": "pathlib._NormalAccessor.listdir", "type": null, "documentation": []}, {"name": "pathlib._NormalAccessor.chmod", "type": null, "documentation": []}, {"name": "pathlib._NormalAccessor.lchmod", "type": null, "documentation": []}, {"name": "pathlib._NormalAccessor.mkdir", "type": null, "documentation": []}, {"name": "pathlib._NormalAccessor.unlink", "type": null, "documentation": []}, {"name": "pathlib._NormalAccessor.rmdir", "type": null, "documentation": []}, {"name": "pathlib._NormalAccessor.rename", "type": null, "documentation": []}, {"name": "pathlib._NormalAccessor.replace", "type": null, "documentation": []}, {"name": "pathlib._NormalAccessor.symlink", "type": null, "documentation": []}, {"name": "pathlib._NormalAccessor.utime", "type": null, "documentation": []}], "instance_variables": [], "inner_classes": [], "documentation": []}, {"name": "pathlib._Selector", "bases": [], "methods": [{"name": "pathlib._Selector.__init__", "asynchronous": false, "params": [{"name": "self", "type": null, "default": null}, {"name": "child_parts", "type": null, "default": null}], "returns": null, "documentation": []}, {"name": "pathlib._Selector.select_from", "asynchronous": false, "params": [{"name": "self", "type": null, "default": null}, {"name": "parent_path", "type": null, "default": null}], "returns": null, "documentation": ["Iterate over all child paths of `parent_path` matched by this\nselector.  This can contain parent_path itself."]}], "class_variables": [], "instance_variables": [], "inner_classes": [], "documentation": ["A selector matches a specific glob pattern part against the children\nof a given path."]}, {"name": "pathlib._TerminatingSelector", "bases": [], "methods": [{"name": "pathlib._TerminatingSelector._select_from", "asynchronous": false, "params": [{"name": "self", "type": null, "default": null}, {"name": "parent_path", "type": null, "default": null}, {"name": "is_dir", "type": null, "default": null}, {"name": "exists", "type": null, "default": null}, {"name": "listdir", "type": null, "default": null}], "returns": null, "documentation": []}], "class_variables": [], "instance_variables": [], "inner_classes": [], "documentation": []}, {"name": "pathlib._PreciseSelector", "bases": ["_Selector"], "methods": [{"name": "pathlib._PreciseSelector.__init__", "asynchronous": false, "params": [{"name": "self", "type": null, "default": null}, {"name": "name", "type": null, "default": null}, {"name": "child_parts", "type": null, "default": null}], "returns": null, "documentation": []}, {"name": "pathlib._PreciseSelector._select_from", "asynchronous": false, "params": [{"name": "self", "type": null, "default": null}, {"name": "parent_path", "type": null, "default": null}, {"name": "is_dir", "type": null, "default": null}, {"name": "exists", "type": null, "default": null}, {"name": "listdir", "type": null, "default": null}], "returns": null, "documentation": []}], "class_variables": [], "instance_variables": [], "inner_classes": [], "documentation": []}, {"name": "pathlib._WildcardSelector", "bases": ["_Selector"], "methods": [{"name": "pathlib._WildcardSelector.__init__", "asynchronous": false, "params": [{"name": "self", "type": null, "default": null}, {"name": "pat", "type": null, "default": null}, {"name": "child_parts", "type": null, "default": null}], "returns": null, "documentation": []}, {"name": "pathlib._WildcardSelector._select_from", "asynchronous": false, "params": [{"name": "self", "type": null, "default": null}, {"name": "parent_path", "type": null, "default": null}, {"name": "is_dir", "type": null, "default": null}, {"name": "exists", "type": null, "default": null}, {"name": "listdir", "type": null, "default": null}], "returns": null, "documentation": []}], "class_variables": [], "instance_variables": [], "inner_classes": [], "documentation": []}, {"name": "pathlib._RecursiveWildcardSelector", "bases": ["_Selector"], "methods": [{"name": "pathlib._RecursiveWildcardSelector.__init__", "asynchronous": false, "params": [{"name": "self", "type": null, "default": null}, {"name": "pat", "type": null, "default": null}, {"name": "child_parts", "type": null, "default": null}], "returns": null, "documentation": []}, {"name": "pathlib._RecursiveWildcardSelector._iterate_directories", "asynchronous": false, "params": [{"name": "self", "type": null, "default": null}, {"name": "parent_path", "type": null, "default": null}, {"name": "is_dir", "type": null, "default": null}, {"name": "listdir", "type": null, "default": null}], "returns": null, "documentation": []}, {"name": "pathlib._RecursiveWildcardSelector._select_from", "asynchronous": false, "params": [{"name": "self", "type": null, "default": null}, {"name": "parent_path", "type": null, "default": null}, {"name": "is_dir", "type": null, "default": null}, {"name": "exists", "type": null, "default": null}, {"name": "listdir", "type": null, "default": null}], "returns": null, "documentation": []}], "class_variables": [], "instance_variables": [], "inner_classes": [], "documentation": []}, {"name": "pathlib._PathParents", "bases": ["Sequence"], "methods": [{"name": "pathlib._PathParents.__init__", "asynchronous": false, "params": [{"name": "self", "type": null, "default": null}, {"name": "path", "type": null, "default": null}], "returns": null, "documentation": []}, {"name": "pathlib._PathParents.__len__", "asynchronous": false, "params": [{"name": "self", "type": null, "default": null}], "returns": null, "documentation": []}, {"name": "pathlib._PathParents.__getitem__", "asynchronous": false, "params": [{"name": "self", "type": null, "default": null}, {"name": "idx", "type": null, "default": null}], "returns": null, "documentation": []}, {"name": "pathlib._PathParents.__repr__", "asynchronous": false, "params": [{"name": "self", "type": null, "default": null}], "returns": null, "documentation": []}], "class_variables": [{"name": "pathlib._PathParents.__slots__", "type": null, "documentation": []}], "instance_variables": [], "inner_classes": [], "documentation": ["This object provides sequence-like access to the logical ancestors\nof a path.  Don't try to construct it yourself.", "Public API"]}, {"name": "pathlib.PurePath", "bases": ["object"], "methods": [{"name": "pathlib.PurePath.__new__", "asynchronous": false, "params": [{"name": "cls", "type": null, "default": null}, {"name": "*args", "type": null, "default": null}], "returns": null, "documentation": ["Construct a PurePath from one or several strings and or existing\nPurePath objects.  The strings and path objects are combined so as\nto yield a canonicalized path, which is incorporated into the\nnew PurePath object."]}, {"name": "pathlib.PurePath.__reduce__", "asynchronous": false, "params": [{"name": "self", "type": null, "default": null}], "returns": null, "documentation": []}, {"name": "pathlib.PurePath._parse_args", "asynchronous": false, "params": [{"name": "cls", "type": null, "default": null}, {"name": "args", "type": null, "default": null}], "returns": null, "documentation": []}, {"name": "pathlib.PurePath._from_parts", "asynchronous": false, "params": [{"name": "cls", "type": null, "default": null}, {"name": "args", "type": null, "default": null}, {"name": "init", "type": null, "default": "..."}], "returns": null, "documentation": []}, {"name": "pathlib.PurePath._from_parsed_parts", "asynchronous": false, "params": [{"name": "cls", "type": null, "default": null}, {"name": "drv", "type": null, "default": null}, {"name": "root", "type": null, "default": null}, {"name": "parts", "type": null, "default": null}, {"name": "init", "type": null, "default": "..."}], "returns": null, "documentation": []}, {"name": "pathlib.PurePath._format_parsed_parts", "asynchronous": false, "params": [{"name": "cls", "type": null, "default": null}, {"name": "drv", "type": null, "default": null}, {"name": "root", "type": null, "default": null}, {"name": "parts", "type": null, "default": null}], "returns": null, "documentation": []}, {"name": "pathlib.PurePath._init", "asynchronous": false, "params": [{"name": "self", "type": null, "default": null}], "returns": null, "documentation": []}, {"name": "pathlib.PurePath._make_child", "asynchronous": false, "params": [{"name": "self", "type": null, "default": null}, {"name": "args", "type": null, "default": null}], "returns": null, "documentation": []}, {"name": "pathlib.PurePath.__str__", "asynchronous": false, "params": [{"name": "self", "type": null, "default": null}], "returns": null, "documentation": ["Return the string representation of the path, suitable for\npassing to system calls."]}, {"name": "pathlib.PurePath.as_posix", "asynchronous": false, "params": [{"name": "self", "type": null, "default": null}], "returns": null, "documentation": ["Return the string representation of the path with forward (/)\nslashes."]}, {"name": "pathlib.PurePath.__bytes__", "asynchronous": false, "params": [{"name": "self", "type": null, "default": null}], "returns": null, "documentation": ["Return the bytes representation of the path.  This is only\nrecommended to use under Unix."]}, {"name": "pathlib.PurePath.__repr__", "asynchronous": false, "params": [{"name": "self", "type": null, "default": null}], "returns": null, "documentation": []}, {"name": "pathlib.PurePath.as_uri", "asynchronous": false, "params": [{"name": "self", "type": null, "default": null}], "returns": null, "documentation": ["Return the path as a 'file' URI."]}, {"name": "pathlib.PurePath._cparts", "asynchronous": false, "params": [{"name": "self", "type": null, "default": null}], "returns": null, "documentation": []}, {"name": "pathlib.PurePath.__eq__", "asynchronous": false, "params": [{"name": "self", "type": null, "default": null}, {"name": "other", "type": null, "default": null}], "returns": null, "documentation": []}, {"name": "pathlib.PurePath.__ne__", "asynchronous": false, "params": [{"name": "self", "type": null, "default": null}, {"name": "other", "type": null, "default": null}], "returns": null, "documentation": []}, {"name": "pathlib.PurePath.__hash__", "asynchronous": false, "params": [{"name": "self", "type": null, "default": null}], "returns": null, "documentation": []}, {"name": "pathlib.PurePath.__lt__", "asynchronous": false, "params": [{"name": "self", "type": null, "default": null}, {"name": "other", "type": null, "default": null}], "returns": null, "documentation": []}, {"name": "pathlib.PurePath.__le__", "asynchronous": false, "params": [{"name": "self", "type": null, "default": null}, {"name": "other", "type": null, "default": null}], "returns": null, "documentation": []}, {"name": "pathlib.PurePath.__gt__", "asynchronous": false, "params": [{"name": "self", "type": null, "default": null}, {"name": "other", "type": null, "default": null}], "returns": null, "documentation": []}, {"name": "pathlib.PurePath.__ge__", "asynchronous": false, "params": [{"name": "self", "type": null, "default": null}, {"name": "other", "type": null, "default": null}], "returns": null, "documentation": []}, {"name": "pathlib.PurePath.anchor", "asynchronous": false, "params": [{"name": "self", "type": null, "default": null}], "returns": null, "documentation": ["The concatenation of the drive and root, or ''."]}, {"name": "pathlib.PurePath.name", "asynchronous": false, "params": [{"name": "self", "type": null, "default": null}], "returns": null, "documentation": ["The final path component, if any."]}, {"name": "pathlib.PurePath.suffix", "asynchronous": false, "params": [{"name": "self", "type": null, "default": null}], "returns": null, "documentation": ["The final component's last suffix, if any."]}, {"name": "pathlib.PurePath.suffixes", "asynchronous": false, "params": [{"name": "self", "type": null, "default": null}], "returns": null, "documentation": ["A list of the final component's suffixes, if any."]}, {"name": "pathlib.PurePath.stem", "asynchronous": false, "params": [{"name": "self", "type": null, "default": null}], "returns": null, "documentation": ["The final path component, minus its last suffix."]}, {"name": "pathlib.PurePath.with_name", "asynchronous": false, "params": [{"name": "self", "type": null, "default": null}, {"name": "name", "type": null, "default": null}], "returns": null, "documentation": ["Return a new path with the file name changed."]}, {"name": "pathlib.PurePath.with_suffix", "asynchronous": false, "params": [{"name": "self", "type": null, "default": null}, {"name": "suffix", "type": null, "default": null}], "returns": null, "documentation": ["Return a new path with the file suffix changed (or added, if none)."]}, {"name": "pathlib.PurePath.relative_to", "asynchronous": false, "params": [{"name": "self", "type": null, "default": null}, {"name": "*other", "type": null, "default": null}], "returns": null, "documentation": ["Return the relative path to another path identified by the passed\narguments.  If the operation is not possible (because this is not\na subpath of the other path), raise ValueError."]}, {"name": "pathlib.PurePath.parts", "asynchronous": false, "params": [{"name": "self", "type": null, "default": null}], "returns": null, "documentation": ["An object providing sequence-like access to the\ncomponents in the filesystem path."]}, {"name": "pathlib.PurePath.joinpath", "asynchronous": false, "params": [{"name": "self", "type": null, "default": null}, {"name": "*args", "type": null, "default": null}], "returns": null, "documentation": ["Combine this path with one or several arguments, and return a\nnew path representing either a subpath (if all arguments are relative\npaths) or a totally different path (if one of the arguments is\nanchored)."]}, {"name": "pathlib.PurePath.__truediv__", "asynchronous": false, "params": [{"name": "self", "type": null, "default": null}, {"name": "key", "type": null, "default": null}], "returns": null, "documentation": []}, {"name": "pathlib.PurePath.__rtruediv__", "asynchronous": false, "params": [{"name": "self", "type": null, "default": null}, {"name": "key", "type": null, "default": null}], "returns": null, "documentation": []}, {"name": "pathlib.PurePath.parent", "asynchronous": false, "params": [{"name": "self", "type": null, "default": null}], "returns": null, "documentation": ["The logical parent of the path."]}, {"name": "pathlib.PurePath.parents", "asynchronous": false, "params": [{"name": "self", "type": null, "default": null}], "returns": null, "documentation": ["A sequence of this path's logical parents."]}, {"name": "pathlib.PurePath.is_absolute", "asynchronous": false, "params": [{"name": "self", "type": null, "default": null}], "returns": null, "documentation": ["True if the path is absolute (has both a root and, if applicable,\na drive)."]}, {"name": "pathlib.PurePath.is_reserved", "asynchronous": false, "params": [{"name": "self", "type": null, "default": null}], "returns": null, "documentation": ["Return True if the path contains one of the special names reserved\nby the system, if any."]}, {"name": "pathlib.PurePath.match", "asynchronous": false, "params": [{"name": "self", "type": null, "default": null}, {"name": "path_pattern", "type": null, "default": null}], "returns": null, "documentation": ["Return True if this path matches the given pattern."]}], "class_variables": [{"name": "pathlib.PurePath.__slots__", "type": null, "documentation": []}, {"name": "pathlib.PurePath.drive", "type": null, "documentation": []}, {"name": "pathlib.PurePath.root", "type": null, "documentation": []}, {"name": "pathlib.PurePath.__div__", "type": null, "documentation": []}, {"name": "pathlib.PurePath.__rdiv__", "type": null, "documentation": []}], "instance_variables": [], "inner_classes": [], "documentation": ["PurePath represents a filesystem path and offers operations which\ndon't imply any actual filesystem I/O.  Depending on your system,\ninstantiating a PurePath will return either a PurePosixPath or a\nPureWindowsPath object.  You can also instantiate either of these classes\ndirectly, regardless of your system."]}, {"name": "pathlib.PurePosixPath", "bases": ["PurePath"], "methods": [], "class_variables": [{"name": "pathlib.PurePosixPath._flavour", "type": null, "documentation": []}, {"name": "pathlib.PurePosixPath.__slots__", "type": null, "documentation": []}], "instance_variables": [], "inner_classes": [], "documentation": []}, {"name": "pathlib.PureWindowsPath", "bases": ["PurePath"], "methods": [], "class_variables": [{"name": "pathlib.PureWindowsPath._flavour", "type": null, "documentation": []}, {"name": "pathlib.PureWindowsPath.__slots__", "type": null, "documentation": []}], "instance_variables": [], "inner_classes": [], "documentation": []}, {"name": "pathlib.Path", "bases": ["PurePath"], "methods": [{"name": "pathlib.Path.__new__", "asynchronous": false, "params": [{"name": "cls", "type": null, "default": null}, {"name": "*args", "type": null, "default": null}, {"name": "**kwargs", "type": null, "default": null}], "returns": null, "documentation": []}, {"name": "pathlib.Path._init", "asynchronous": false, "params": [{"name": "self", "type": null, "default": null}, {"name": "template", "type": null, "default": "..."}], "returns": null, "documentation": []}, {"name": "pathlib.Path._make_child_relpath", "asynchronous": false, "params": [{"name": "self", "type": null, "default": null}, {"name": "part", "type": null, "default": null}], "returns": null, "documentation": []}, {"name": "pathlib.Path._opener", "asynchronous": false, "params": [{"name": "self", "type": null, "default": null}, {"name": "name", "type": null, "default": null}, {"name": "flags", "type": null, "default": null}, {"name": "mode", "type": null, "default": "..."}], "returns": null, "documentation": []}, {"name": "pathlib.Path._raw_open", "asynchronous": false, "params": [{"name": "self", "type": null, "default": null}, {"name": "flags", "type": null, "default": null}, {"name": "mode", "type": null, "default": "..."}], "returns": null, "documentation": ["Open the file pointed by this path and return a file descriptor,\nas os.open() does."]}, {"name": "pathlib.Path.cwd", "asynchronous": false, "params": [{"name": "cls", "type": null, "default": null}], "returns": null, "documentation": ["Return a new path pointing to the current working directory\n(as returned by os.getcwd()).", "Public API"]}, {"name": "pathlib.Path.iterdir", "asynchronous": false, "params": [{"name": "self", "type": null, "default": null}], "returns": null, "documentation": ["Iterate over the files in this directory.  Does not yield any\nresult for the special paths '.' and '..'."]}, {"name": "pathlib.Path.glob", "asynchronous": false, "params": [{"name": "self", "type": null, "default": null}, {"name": "pattern", "type": null, "default": null}], "returns": null, "documentation": ["Iterate over this subtree and yield all existing files (of any\nkind, including directories) matching the given pattern."]}, {"name": "pathlib.Path.rglob", "asynchronous": false, "params": [{"name": "self", "type": null, "default": null}, {"name": "pattern", "type": null, "default": null}], "returns": null, "documentation": ["Recursively yield all existing files (of any kind, including\ndirectories) matching the given pattern, anywhere in this subtree."]}, {"name": "pathlib.Path.absolute", "asynchronous": false, "params": [{"name": "self", "type": null, "default": null}], "returns": null, "documentation": ["Return an absolute version of this path.  This function works\neven if the path doesn't point to anything.\n\nNo normalization is done, i.e. all '.' and '..' will be kept along.\nUse resolve() to get the canonical path to a file."]}, {"name": "pathlib.Path.resolve", "asynchronous": false, "params": [{"name": "self", "type": null, "default": null}], "returns": null, "documentation": ["Make the path absolute, resolving all symlinks on the way and also\nnormalizing it (for example turning slashes into backslashes under\nWindows)."]}, {"name": "pathlib.Path.stat", "asynchronous": false, "params": [{"name": "self", "type": null, "default": null}], "returns": null, "documentation": ["Return the result of the stat() system call on this path, like\nos.stat() does."]}, {"name": "pathlib.Path.owner", "asynchronous": false, "params": [{"name": "self", "type": null, "default": null}], "returns": null, "documentation": ["Return the login name of the file owner."]}, {"name": "pathlib.Path.group", "asynchronous": false, "params": [{"name": "self", "type": null, "default": null}], "returns": null, "documentation": ["Return the group name of the file gid."]}, {"name": "pathlib.Path.open", "asynchronous": false, "params": [{"name": "self", "type": null, "default": null}, {"name": "mode", "type": null, "default": "..."}, {"name": "buffering", "type": null, "default": "..."}, {"name": "encoding", "type": null, "default": "..."}, {"name": "errors", "type": null, "default": "..."}, {"name": "newline", "type": null, "default": "..."}], "returns": null, "documentation": ["Open the file pointed by this path and return a file object, as\nthe built-in open() function does."]}, {"name": "pathlib.Path.touch", "asynchronous": false, "params": [{"name": "self", "type": null, "default": null}, {"name": "mode", "type": null, "default": "..."}, {"name": "exist_ok", "type": null, "default": "..."}], "returns": null, "documentation": ["Create this file with the given access mode, if it doesn't exist."]}, {"name": "pathlib.Path.mkdir", "asynchronous": false, "params": [{"name": "self", "type": null, "default": null}, {"name": "mode", "type": null, "default": "..."}, {"name": "parents", "type": null, "default": "..."}], "returns": null, "documentation": []}, {"name": "pathlib.Path.chmod", "asynchronous": false, "params": [{"name": "self", "type": null, "default": null}, {"name": "mode", "type": null, "default": null}], "returns": null, "documentation": ["Change the permissions of the path, like os.chmod()."]}, {"name": "pathlib.Path.lchmod", "asynchronous": false, "params": [{"name": "self", "type": null, "default": null}, {"name": "mode", "type": null, "default": null}], "returns": null, "documentation": ["Like chmod(), except if the path points to a symlink, the symlink's\npermissions are changed, rather than its target's."]}, {"name": "pathlib.Path.unlink", "asynchronous": false, "params": [{"name": "self", "type": null, "default": null}], "returns": null, "documentation": ["Remove this file or link.\nIf the path is a directory, use rmdir() instead."]}, {"name": "pathlib.Path.rmdir", "asynchronous": false, "params": [{"name": "self", "type": null, "default": null}], "returns": null, "documentation": ["Remove this directory.  The directory must be empty."]}, {"name": "pathlib.Path.lstat", "asynchronous": false, "params": [{"name": "self", "type": null, "default": null}], "returns": null, "documentation": ["Like stat(), except if the path points to a symlink, the symlink's\nstatus information is returned, rather than its target's."]}, {"name": "pathlib.Path.rename", "asynchronous": false, "params": [{"name": "self", "type": null, "default": null}, {"name": "target", "type": null, "default": null}], "returns": null, "documentation": ["Rename this path to the given path."]}, {"name": "pathlib.Path.replace", "asynchronous": false, "params": [{"name": "self", "type": null, "default": null}, {"name": "target", "type": null, "default": null}], "returns": null, "documentation": ["Rename this path to the given path, clobbering the existing\ndestination if it exists."]}, {"name": "pathlib.Path.symlink_to", "asynchronous": false, "params": [{"name": "self", "type": null, "default": null}, {"name": "target", "type": null, "default": null}, {"name": "target_is_directory", "type": null, "default": "..."}], "returns": null, "documentation": ["Make this path a symlink pointing to the given path.\nNote the order of arguments (self, target) is the reverse of os.symlink's."]}, {"name": "pathlib.Path.exists", "asynchronous": false, "params": [{"name": "self", "type": null, "default": null}], "returns": null, "documentation": ["Whether this path exists.", "Convenience functions for querying the stat results"]}, {"name": "pathlib.Path.is_dir", "asynchronous": false, "params": [{"name": "self", "type": null, "default": null}], "returns": null, "documentation": ["Whether this path is a directory."]}, {"name": "pathlib.Path.is_file", "asynchronous": false, "params": [{"name": "self", "type": null, "default": null}], "returns": null, "documentation": ["Whether this path is a regular file (also True for symlinks pointing\nto regular files)."]}, {"name": "pathlib.Path.is_symlink", "asynchronous": false, "params": [{"name": "self", "type": null, "default": null}], "returns": null, "documentation": ["Whether this path is a symbolic link."]}, {"name": "pathlib.Path.is_block_device", "asynchronous": false, "params": [{"name": "self", "type": null, "default": null}], "returns": null, "documentation": ["Whether this path is a block device."]}, {"name": "pathlib.Path.is_char_device", "asynchronous": false, "params": [{"name": "self", "type": null, "default": null}], "returns": null, "documentation": ["Whether this path is a character device."]}, {"name": "pathlib.Path.is_fifo", "asynchronous": false, "params": [{"name": "self", "type": null, "default": null}], "returns": null, "documentation": ["Whether this path is a FIFO."]}, {"name": "pathlib.Path.is_socket", "asynchronous": false, "params": [{"name": "self", "type": null, "default": null}], "returns": null, "documentation": ["Whether this path is a socket."]}], "class_variables": [{"name": "pathlib.Path.__slots__", "type": null, "documentation": []}], "instance_variables": [], "inner_classes": [], "documentation": ["Filesystem-accessing classes"]}, {"name": "pathlib.PosixPath", "bases": ["Path", "PurePosixPath"], "methods": [], "class_variables": [{"name": "pathlib.PosixPath.__slots__", "type": null, "documentation": []}], "instance_variables": [], "inner_classes": [], "documentation": []}, {"name": "pathlib.WindowsPath", "bases": ["Path", "PureWindowsPath"], "methods": [], "class_variables": [{"name": "pathlib.WindowsPath.__slots__", "type": null, "documentation": []}], "instance_variables": [], "inner_classes": [], "documentation": []}], "exports": [{"name": "pathlib.Path", "xref": {"fqname": "pathlib.Path", "project": null}}, {"name": "pathlib.PosixPath", "xref": {"fqname": "pathlib.PosixPath", "project": null}}, {"name": "pathlib.PurePath", "xref": {"fqname": "pathlib.PurePath", "project": null}}, {"name": "pathlib.PurePosixPath", "xref": {"fqname": "pathlib.PurePosixPath", "project": null}}, {"name": "pathlib.PureWindowsPath", "xref": {"fqname": "pathlib.PureWindowsPath", "project": null}}, {"name": "pathlib.WindowsPath", "xref": {"fqname": "pathlib.WindowsPath", "project": null}}]}]}