{"name": "rbac-library", "metadata": {"name": "rbac-library", "version": "0.1.0", "classifiers": ["Framework :: Django", "License :: OSI Approved :: MIT License", "Operating System :: OS Independent", "Programming Language :: Python :: 3"], "home_page": null, "license": null, "documentation_url": null, "dependencies": ["django"], "summary": "Role-Based Access Control Library for Django", "upload_time": 1733352287}, "documentation": [""], "modules": [{"name": "rbac.utils", "documentation": [], "functions": [{"name": "rbac.utils.assign_role", "asynchronous": false, "params": [{"name": "user", "type": null, "default": null}, {"name": "role_name", "type": null, "default": null}], "returns": null, "documentation": ["Assign a specific role to a user."]}, {"name": "rbac.utils.remove_role", "asynchronous": false, "params": [{"name": "user", "type": null, "default": null}, {"name": "role_name", "type": null, "default": null}], "returns": null, "documentation": ["Remove a specific role from a user."]}], "variables": [], "classes": [], "exports": []}, {"name": "rbac.permissions", "documentation": [], "functions": [{"name": "rbac.permissions.check_user_role", "asynchronous": false, "params": [{"name": "user", "type": null, "default": null}, {"name": "role", "type": null, "default": null}], "returns": null, "documentation": ["Check if a user has a specific role."]}, {"name": "rbac.permissions.is_admin", "asynchronous": false, "params": [{"name": "user", "type": null, "default": null}], "returns": null, "documentation": ["Check if the user is an admin."]}, {"name": "rbac.permissions.is_staff", "asynchronous": false, "params": [{"name": "user", "type": null, "default": null}], "returns": null, "documentation": ["Check if the user is a staff member."]}], "variables": [], "classes": [], "exports": []}, {"name": "rbac", "documentation": [], "functions": [], "variables": [], "classes": [], "exports": []}, {"name": "rbac.decorators", "documentation": [], "functions": [{"name": "rbac.decorators.role_required", "asynchronous": false, "params": [{"name": "role", "type": null, "default": null}], "returns": null, "documentation": ["Decorator to restrict view access to a specific role."]}], "variables": [], "classes": [], "exports": []}]}